{
  "uuid": "aYzL",
  "title": "Étude d'une méthode de Monte Carlo",
  "chapter": "Probabilité continue",
  "subchapter": "Lois des grands nombres, théorème central limite",
  "theme": "méthode de Monte Carlo, loi forte des grands nombres, théorème central limite",
  "difficulty": null,
  "author": "Maxime Nguyen",
  "organization": "AMSCC",
  "video_id": "",
  "created_at": "2022-09-24",
  "updated_at": "2025-08-22T12:39:55.222Z",
  "content": [
    {
      "id": "block_1",
      "type": "text",
      "latex": "On souhaite calculer à l'aide d'une méthode de Monte Carlo une approximation de l'intégrale $$I=\\int_0^1 \\sin(\\sqrt{x})dx$$ \n\tSoit $(X_i)_{i \\in \\mathbb{N}^*}$ une suite de variables aléatoires indépendantes identiquement distribuées selon une loi uniforme $\\mathcal{U}([0;1])$.",
      "html": "<p>On souhaite calculer à l’aide d’une méthode de Monte Carlo une approximation de l’intégrale <span>\\[I=\\int_0^1 \\sin(\\sqrt{x})dx\\]</span>\nSoit <span>\\((X_i)_{i \\in \\mathbb{N}^*}\\)</span> une suite de variables aléatoires indépendantes identiquement distribuées selon une loi uniforme <span>\\(\\mathcal{U}([0;1])\\)</span>.</p>",
      "order": 1
    },
    {
      "id": "block_2",
      "type": "question",
      "latex": "Démontrer que si on définit la suite de variables aléatoires $(I_n)$ par \n\t\t$$I_n = \\frac{1}{n}\\sum_{k=1}^n \\sin\\left( \\sqrt{X_k} \\right)$$\n\t\talors la suite $(I_n)$ converge presque sûrement vers la constante $I$.",
      "html": "<p>Démontrer que si on définit la suite de variables aléatoires <span>\\((I_n)\\)</span> par\n<span>\\[I_n = \\frac{1}{n}\\sum_{k=1}^n \\sin\\left( \\sqrt{X_k} \\right)\\]</span>\nalors la suite <span>\\((I_n)\\)</span> converge presque sûrement vers la constante <span>\\(I\\)</span>.</p>",
      "order": 2
    },
    {
      "id": "block_3",
      "type": "reponse",
      "latex": "Les variables $\\left(\\sin\\left( \\sqrt{X_k} \\right) \\right)_i$ sont indépendantes et identiquement distribuées, elles admettent en outre une espérance qui se calcule à l'aide du théorème de transfert. Soit $f$ la densité d'une loi uniforme sur $[0;1]$. Alors $\\mathbb{E}(X_1) = \\int \\sin\\left( \\sqrt{x} \\right) f(x)dx = \\int_0^1 \\sin\\left( \\sqrt{x} \\right)dx = I$.\n\t\t\n\t\tD'après la loi forte de grands nombres, la suite de variables aléatoires $(I_n)$ converge donc presque sûrement vers $\\mathbb{E}(X_1) = I$.",
      "html": "<p>Les variables <span>\\(\\left(\\sin\\left( \\sqrt{X_k} \\right) \\right)_i\\)</span> sont indépendantes et identiquement distribuées, elles admettent en outre une espérance qui se calcule à l’aide du théorème de transfert. Soit <span>\\(f\\)</span> la densité d’une loi uniforme sur <span>\\([0;1]\\)</span>. Alors <span>\\(\\mathbb{E}(X_1) = \\int \\sin\\left( \\sqrt{x} \\right) f(x)dx = \\int_0^1 \\sin\\left( \\sqrt{x} \\right)dx = I\\)</span>.</p>\n<p>D’après la loi forte de grands nombres, la suite de variables aléatoires <span>\\((I_n)\\)</span> converge donc presque sûrement vers <span>\\(\\mathbb{E}(X_1) = I\\)</span>.</p>",
      "order": 3
    },
    {
      "id": "block_4",
      "type": "question",
      "latex": "Compléter le code Python ci-dessous, comportant deux champs manquants, afin qu'il affiche une approximation de $I$.\n\t\t\n\t{\\centering \\fbox{\\BUseVerbatim{aYzLpython}}\\par}",
      "html": "<p>Compléter le code Python ci-dessous, comportant deux champs manquants, afin qu’il affiche une approximation de <span>\\(I\\)</span>.</p>",
      "order": 4
    },
    {
      "id": "block_5",
      "type": "reponse",
      "latex": "{\\centering \\fbox{\\BUseVerbatim{aYzLpythonsolution}}\\par}",
      "html": "",
      "order": 5
    },
    {
      "id": "block_6",
      "type": "text",
      "latex": "Pour tout $k \\in \\mathbb{N}^*$, on pose $Y_k= \\sin\\left( \\sqrt{X_k} \\right)$. Les variables aléatoires $(X_k)$ étant i.i.d., les variables aléatoires $(Y_k)$ le sont aussi et on note $\\mu$ leur espérance et $\\sigma^2$ leur variance.",
      "html": "<p>Pour tout <span>\\(k \\in \\mathbb{N}^*\\)</span>, on pose <span>\\(Y_k= \\sin\\left( \\sqrt{X_k} \\right)\\)</span>. Les variables aléatoires <span>\\((X_k)\\)</span> étant i.i.d., les variables aléatoires <span>\\((Y_k)\\)</span> le sont aussi et on note <span>\\(\\mu\\)</span> leur espérance et <span>\\(\\sigma^2\\)</span> leur variance.</p>",
      "order": 6
    },
    {
      "id": "block_7",
      "type": "question",
      "latex": "Calculer l'espérance et la variance de la variable aléatoire $I_n$ en fonction de $\\mu$, $\\sigma$ et $n$.",
      "html": "<p>Calculer l’espérance et la variance de la variable aléatoire <span>\\(I_n\\)</span> en fonction de <span>\\(\\mu\\)</span>, <span>\\(\\sigma\\)</span> et <span>\\(n\\)</span>.</p>",
      "order": 7
    },
    {
      "id": "block_8",
      "type": "reponse",
      "latex": "Par linéarité de l'espérance, $\\mathbb{E}(I_n) = \\frac{1}{n} \\times n \\times I =I $.\n\t\t\tPar propriétés de la variance et indépendance des variables dans la somme, $V(I_n) = \\frac{1}{n^2} \\times n \\times V(Y_1) = \\frac{V(Y_1)}{n} = \\frac{\\sigma^2}{n}$.",
      "html": "<p>Par linéarité de l’espérance, <span>\\(\\mathbb{E}(I_n) = \\frac{1}{n} \\times n \\times I =I\\)</span>.\nPar propriétés de la variance et indépendance des variables dans la somme, <span>\\(V(I_n) = \\frac{1}{n^2} \\times n \\times V(Y_1) = \\frac{V(Y_1)}{n} = \\frac{\\sigma^2}{n}\\)</span>.</p>",
      "order": 8
    },
    {
      "id": "block_9",
      "type": "question",
      "latex": "Déterminer, en justifiant, une approximation de la loi de la variable aléatoire $$\\frac{\\sqrt{n}}{\\sigma}(I_n-I)$$\n\t\t\tlorsque $n$ est suffisamment grand.",
      "html": "<p>Déterminer, en justifiant, une approximation de la loi de la variable aléatoire <span>\\[\\frac{\\sqrt{n}}{\\sigma}(I_n-I)\\]</span>\nlorsque <span>\\(n\\)</span> est suffisamment grand.</p>",
      "order": 9
    },
    {
      "id": "block_10",
      "type": "reponse",
      "latex": "Les variables $Y_k$ sont indépendantes, identiquement distribuées, admettent une espérance et une variance finies, donc d'après le Théorème Central Limite, la variable \n\t\t\t$$\\frac{\\frac{1}{n}\\sum_{k=1}^n Y_k - I  }{\\frac{\\sigma}{\\sqrt{n}}} = \n\t\t\t\\frac{ \\sum_{k=1}^n \\frac{Y_k}{n} - \\mathbb{E}\\left(\\sum_{k=1}^n \\frac{Y_k}{n}  \\right) }{\\sigma\\left(\\sum_{k=1}^n \\frac{Y_k}{n}  \\right)}$$\n\t\t\tsuit approximativement une loi normale centrée réduite.",
      "html": "<p>Les variables <span>\\(Y_k\\)</span> sont indépendantes, identiquement distribuées, admettent une espérance et une variance finies, donc d’après le Théorème Central Limite, la variable\n<span>\\[\\frac{\\frac{1}{n}\\sum_{k=1}^n Y_k - I  }{\\frac{\\sigma}{\\sqrt{n}}} = \n            \\frac{ \\sum_{k=1}^n \\frac{Y_k}{n} - \\mathbb{E}\\left(\\sum_{k=1}^n \\frac{Y_k}{n}  \\right) }{\\sigma\\left(\\sum_{k=1}^n \\frac{Y_k}{n}  \\right)}\\]</span>\nsuit approximativement une loi normale centrée réduite.</p>",
      "order": 10
    },
    {
      "id": "block_11",
      "type": "question",
      "latex": "En déduire le nombre d'itérations $N_0$ (dépendant de $\\sigma$) à partir duquel la suite $(I_n)$ réalise une approximation de $I$ à $10^{-3}$ près avec une confiance de $95\\%$.",
      "html": "<p>En déduire le nombre d’itérations <span>\\(N_0\\)</span> (dépendant de <span>\\(\\sigma\\)</span>) à partir duquel la suite <span>\\((I_n)\\)</span> réalise une approximation de <span>\\(I\\)</span> à <span>\\(10^{-3}\\)</span> près avec une confiance de <span>\\(95\\%\\)</span>.</p>",
      "order": 11
    },
    {
      "id": "block_12",
      "type": "reponse",
      "latex": "On cherche le rang à partir duquel $\\PP(|I_n-I|<\\varepsilon) \\geq 0.95$ où $\\varepsilon = 10^{-3}$. Or \n\t\t\t$$\\begin{align*}\n\t\t\t\t\\PP(|I_n-I|<\\varepsilon) &= \\PP(-\\varepsilon < I_n-I < \\varepsilon) \\\\\n\t\t\t\t&= \\PP\\left(-\\frac{\\sqrt{n}}{\\sigma}\\varepsilon < \\frac{\\sqrt{n}}{\\sigma} (I_n-I) < \\frac{\\sqrt{n}}{\\sigma}\\varepsilon \\right) \\\\\n\t\t\t\t&\\approx \\PP\\left(-\\frac{\\sqrt{n}}{\\sigma}\\varepsilon < Z < \\frac{\\sqrt{n}}{\\sigma}\\varepsilon \\right) \\text{ où } Z \\sim \\mathcal{N}(0,1)\n\t\t\t\\end{align*}$$\n\t\t\tOr par lecture de tables, $\\PP(-1.96 < Z < 1.96) \\approx 0.95$ donc il suffit de prendre $n$ tel que $\\frac{\\sqrt{n}}{\\sigma}\\varepsilon \\geq 1.96$ i.e.\n\t\t\t$$n \\geq 10^6 \\left(1.96 \\sigma\\right)^2$$",
      "html": "<p>On cherche le rang à partir duquel <span>\\(\\PP(|I_n-I|&lt;\\varepsilon) \\geq 0.95\\)</span> où <span>\\(\\varepsilon = 10^{-3}\\)</span>. Or\n<span>\\[\\begin{align*}\n                \\PP(|I_n-I|&lt;\\varepsilon) &amp;= \\PP(-\\varepsilon &lt; I_n-I &lt; \\varepsilon) \\\\\n                &amp;= \\PP\\left(-\\frac{\\sqrt{n}}{\\sigma}\\varepsilon &lt; \\frac{\\sqrt{n}}{\\sigma} (I_n-I) &lt; \\frac{\\sqrt{n}}{\\sigma}\\varepsilon \\right) \\\\\n                &amp;\\approx \\PP\\left(-\\frac{\\sqrt{n}}{\\sigma}\\varepsilon &lt; Z &lt; \\frac{\\sqrt{n}}{\\sigma}\\varepsilon \\right) \\text{ où } Z \\sim \\mathcal{N}(0,1)\n            \\end{align*}\\]</span>\nOr par lecture de tables, <span>\\(\\PP(-1.96 &lt; Z &lt; 1.96) \\approx 0.95\\)</span> donc il suffit de prendre <span>\\(n\\)</span> tel que <span>\\(\\frac{\\sqrt{n}}{\\sigma}\\varepsilon \\geq 1.96\\)</span> i.e.\n<span>\\[n \\geq 10^6 \\left(1.96 \\sigma\\right)^2\\]</span></p>",
      "order": 12
    },
    {
      "id": "block_13",
      "type": "question",
      "latex": "Soit la variable \n\t\t\t$$V_n = \\frac{1}{2n} \\sum_{k=1}^n (Y_{2k}-Y_{2k-1})^2$$\n\t\t\tVérifier que la suite $(V_n)$ permet d'approcher la valeur de $\\sigma^2$.",
      "html": "<p>Soit la variable\n<span>\\[V_n = \\frac{1}{2n} \\sum_{k=1}^n (Y_{2k}-Y_{2k-1})^2\\]</span>\nVérifier que la suite <span>\\((V_n)\\)</span> permet d’approcher la valeur de <span>\\(\\sigma^2\\)</span>.</p>",
      "order": 13
    },
    {
      "id": "block_14",
      "type": "reponse",
      "latex": "On calcule \n\t\t\t$$\\begin{align*}\n\t\t\t\t\\mathbb{E}((Y_{2k}-Y_{2k-1})^2) &= \\mathbb{E}(Y_{2k}^2-2Y_{2k}Y_{2k-1} + Y_{2k-1}^2) \\\\\n\t\t\t\t&= \\mathbb{E}(Y_{2k}^2) - 2 \\mathbb{E}(Y_{2k}Y_{2k-1}) +\\mathbb{E}(Y_{2k-1}^2) \\text{ par linéarité } \\\\\n\t\t\t\t&= 2\\mathbb{E}(Y_{2k}^2)- 2 \\mathbb{E}(Y_{2k}Y_{2k-1}) \\text{ par identique distribution } \\\\\n\t\t\t\t&= 2\\mathbb{E}(Y_{2k}^2)- 2 \\mathbb{E}(Y_{2k})  \\mathbb{E}(Y_{2k-1}) \\text{ par indépendance} \\\\\n\t\t\t\t&= 2\\mathbb{E}(Y_{2k}^2)- 2 \\mathbb{E}(Y_{2k})^2 \\\\\n\t\t\t\t&= 2\\mathbb{E}(Y_{1}^2)- 2 \\mathbb{E}(Y_{1})^2 \\\\\n\t\t\t\t&= 2V(Y_1) \n\t\t\t\\end{align*}$$\n\t\t\tdonc d'après la loi forte des grands nombres, $\\frac{1}{n} \\sum_{k=1}^n (Y_{2k}-Y_{2k-1})^2$ converge simplement vers $2V(Y_1)$, ce qui répond à la question posée.",
      "html": "<p>On calcule\n<span>\\[\\begin{align*}\n                \\mathbb{E}((Y_{2k}-Y_{2k-1})^2) &amp;= \\mathbb{E}(Y_{2k}^2-2Y_{2k}Y_{2k-1} + Y_{2k-1}^2) \\\\\n                &amp;= \\mathbb{E}(Y_{2k}^2) - 2 \\mathbb{E}(Y_{2k}Y_{2k-1}) +\\mathbb{E}(Y_{2k-1}^2) \\text{ par linéarité } \\\\\n                &amp;= 2\\mathbb{E}(Y_{2k}^2)- 2 \\mathbb{E}(Y_{2k}Y_{2k-1}) \\text{ par identique distribution } \\\\\n                &amp;= 2\\mathbb{E}(Y_{2k}^2)- 2 \\mathbb{E}(Y_{2k})  \\mathbb{E}(Y_{2k-1}) \\text{ par indépendance} \\\\\n                &amp;= 2\\mathbb{E}(Y_{2k}^2)- 2 \\mathbb{E}(Y_{2k})^2 \\\\\n                &amp;= 2\\mathbb{E}(Y_{1}^2)- 2 \\mathbb{E}(Y_{1})^2 \\\\\n                &amp;= 2V(Y_1) \n            \\end{align*}\\]</span>\ndonc d’après la loi forte des grands nombres, <span>\\(\\frac{1}{n} \\sum_{k=1}^n (Y_{2k}-Y_{2k-1})^2\\)</span> converge simplement vers <span>\\(2V(Y_1)\\)</span>, ce qui répond à la question posée.</p>",
      "order": 14
    }
  ],
  "artifacts": {
    "tikz": [],
    "geogebra": [],
    "code": [],
    "video": null
  },
  "source_hash": "c41e42f7190b937ab8e0070c6391adf9cabd1c03f34d044a23bc4ecff0b4ddc9"
}