{
  "uuid": "Lmme",
  "title": "Fonction de $n$ variables et laplacien nul",
  "chapter": "Fonction de plusieurs variables",
  "subchapter": "Différentiabilité",
  "theme": "calcul différentiel",
  "difficulty": null,
  "author": "",
  "organization": "AMSCC",
  "video_id": "",
  "created_at": "2023-03-09",
  "updated_at": "2025-08-25T13:14:27.070Z",
  "content": [
    {
      "id": "block_1",
      "type": "question",
      "latex": "Soit $g \\colon ]0;+\\infty[ \\to \\R$ une fonction de classe $\\mathcal{C}^2$. Soit un entier $n \\geq 2$ et $f \\colon \\R^n \\backslash \\{0\\} \\to \\R$ définie par $f(x_1,...,x_n) = g(\\sqrt{\\sum_{i=1}^n x_i^2})$. \n\nOn note $\\Delta f = \\sum\\limits_{i=1}^{n} \\frac{\\partial^2 f}{\\partial x_i^2}$ le laplacien de $f$. On pose $r=\\sqrt{\\sum\\limits_{i=1}^n x_i^2}$.",
      "html": "<p>Soit <span class=\"math inline\">\\(g \\colon ]0;+\\infty[ \\to \\R\\)</span> une fonction de classe <span class=\"math inline\">\\(\\mathcal{C}^2\\)</span>. Soit un entier <span class=\"math inline\">\\(n \\geq 2\\)</span> et <span class=\"math inline\">\\(f \\colon \\R^n \\backslash \\{0\\} \\to \\R\\)</span> définie par <span class=\"math inline\">\\(f(x_1,...,x_n) = g(\\sqrt{\\sum_{i=1}^n x_i^2})\\)</span>.</p>\n<p>On note <span class=\"math inline\">\\(\\Delta f = \\sum\\limits_{i=1}^{n} \\frac{\\partial^2 f}{\\partial x_i^2}\\)</span> le laplacien de <span class=\"math inline\">\\(f\\)</span>. On pose <span class=\"math inline\">\\(r=\\sqrt{\\sum\\limits_{i=1}^n x_i^2}\\)</span>.</p>",
      "order": 1
    },
    {
      "id": "block_2",
      "type": "question",
      "latex": "Démontrer que pour tout $x=(x_1,...,x_n) \\in \\R^n \\backslash \\{0\\}$, $\\Delta f(x) = g''(r)+ \\frac{n-1}{r}g'(r)$.",
      "html": "<p>Démontrer que pour tout <span class=\"math inline\">\\(x=(x_1,...,x_n) \\in \\R^n \\backslash \\{0\\}\\)</span>, <span class=\"math inline\">\\(\\Delta f(x) = g&#39;&#39;(r)+ \\frac{n-1}{r}g&#39;(r)\\)</span>.</p>",
      "order": 2
    },
    {
      "id": "block_3",
      "type": "reponse",
      "latex": "On applique la règle des chaînes en voyant $r$ comme une fonction de $n$ variables : \n\t      \t$$\\frac{\\partial f}{\\partial x_i} = \\frac{x_i}{r}g'(r)$$\n\t      \tpuis \n\t      \t$$\\frac{\\partial^2 f}{\\partial x_i^2} = \\left(\\frac{1}{r}- \\frac{x_i}{r^2} \\frac{\\partial r}{\\partial x_i}\\right)g'(r) + \\frac{x_i^2}{r^2}g''(r) = \\frac{r^2-x_i^2}{r^3}g'(r) + \\frac{x_i^2}{r^2}g''(r)  $$\n\t      \tIl reste à sommer pour $i$ variant de $1$ à $n$ pour avoir le résultat.",
      "html": "<p>On applique la règle des chaînes en voyant <span class=\"math inline\">\\(r\\)</span> comme une fonction de <span class=\"math inline\">\\(n\\)</span> variables :\n<span class=\"math display\">\\[\\frac{\\partial f}{\\partial x_i} = \\frac{x_i}{r}g&#39;(r)\\]</span>\npuis\n<span class=\"math display\">\\[\\frac{\\partial^2 f}{\\partial x_i^2} = \\left(\\frac{1}{r}- \\frac{x_i}{r^2} \\frac{\\partial r}{\\partial x_i}\\right)g&#39;(r) + \\frac{x_i^2}{r^2}g&#39;&#39;(r) = \\frac{r^2-x_i^2}{r^3}g&#39;(r) + \\frac{x_i^2}{r^2}g&#39;&#39;(r)\\]</span>\nIl reste à sommer pour <span class=\"math inline\">\\(i\\)</span> variant de <span class=\"math inline\">\\(1\\)</span> à <span class=\"math inline\">\\(n\\)</span> pour avoir le résultat.</p>",
      "order": 3
    },
    {
      "id": "block_4",
      "type": "question",
      "latex": "Déterminer l'ensemble des fonctions $g$ telles que $\\Delta f = 0$.",
      "html": "<p>Déterminer l’ensemble des fonctions <span class=\"math inline\">\\(g\\)</span> telles que <span class=\"math inline\">\\(\\Delta f = 0\\)</span>.</p>",
      "order": 4
    },
    {
      "id": "block_5",
      "type": "reponse",
      "latex": "On en déduit que $\\Delta f =0$ si et seulement si $g'$ est solution de l'équation différentielle linéaire du premier ordre\n\t      \t$$y'+ \\frac{n-1}{r}y = 0$$\n\t      \td'où $g'(r) = \\frac{k_1}{r^{n-1}}$ (avec $k_1 \\in \\R$) d'où $g(r) = \\frac{k_1}{r^{n-2}}+k_2$ si $n \\geq 3$ et $g(r) = k_1\\ln(r) + k_2$ si $n=2$.",
      "html": "<p>On en déduit que <span class=\"math inline\">\\(\\Delta f =0\\)</span> si et seulement si <span class=\"math inline\">\\(g&#39;\\)</span> est solution de l’équation différentielle linéaire du premier ordre\n<span class=\"math display\">\\[y&#39;+ \\frac{n-1}{r}y = 0\\]</span>\nd’où <span class=\"math inline\">\\(g&#39;(r) = \\frac{k_1}{r^{n-1}}\\)</span> (avec <span class=\"math inline\">\\(k_1 \\in \\R\\)</span>) d’où <span class=\"math inline\">\\(g(r) = \\frac{k_1}{r^{n-2}}+k_2\\)</span> si <span class=\"math inline\">\\(n \\geq 3\\)</span> et <span class=\"math inline\">\\(g(r) = k_1\\ln(r) + k_2\\)</span> si <span class=\"math inline\">\\(n=2\\)</span>.</p>",
      "order": 5
    }
  ],
  "artifacts": {
    "tikz": [],
    "geogebra": [],
    "code": [],
    "video": null
  },
  "source_hash": "714e74ace57aae59bd642a73d1b1147556ae531a401c254a84e23711f11b669e"
}