{
  "uuid": "t0mY",
  "title": "Produit matriciel",
  "chapter": "Matrice",
  "subchapter": "Propriétés élémentaires, généralités",
  "theme": "calcul matriciel",
  "difficulty": null,
  "author": "",
  "organization": "AMSCC",
  "video_id": "",
  "created_at": "2022-12-15",
  "updated_at": "2025-08-25T13:15:26.381Z",
  "content": [
    {
      "id": "block_1",
      "type": "text",
      "latex": "On considère les matrices suivantes:\n$$\nA=\\left(\\begin{array}{lll}\n\t1 & 2 & 3\n\\end{array}\\right) \\quad B=\\left(\\begin{array}{c}\n\t1 \\\\\n\t-2\n\\end{array}\\right) \\quad C=\\left(\\begin{array}{cc}\n\t2 & 1 \\\\\n\t-3 & 0 \\\\\n\t1 & 2\n\\end{array}\\right)$$ \n$$D=\\left(\\begin{array}{cc}\n\t-2 & 5 \\\\\n\t5 & 0\n\\end{array}\\right) \\quad E=\\left(\\begin{array}{ccc}\n\t-1 & 1 & 3 \\\\\n\t-1 & -4 & 0 \\\\\n\t0 & 2 & 5\n\\end{array}\\right)\n$$",
      "html": "<p>On considère les matrices suivantes:\n<span class=\"math display\">\\[A=\\left(\\begin{array}{lll}\n    1 &amp; 2 &amp; 3\n\\end{array}\\right) \\quad B=\\left(\\begin{array}{c}\n    1 \\\\\n    -2\n\\end{array}\\right) \\quad C=\\left(\\begin{array}{cc}\n    2 &amp; 1 \\\\\n    -3 &amp; 0 \\\\\n    1 &amp; 2\n\\end{array}\\right)\\]</span>\n<span class=\"math display\">\\[D=\\left(\\begin{array}{cc}\n    -2 &amp; 5 \\\\\n    5 &amp; 0\n\\end{array}\\right) \\quad E=\\left(\\begin{array}{ccc}\n    -1 &amp; 1 &amp; 3 \\\\\n    -1 &amp; -4 &amp; 0 \\\\\n    0 &amp; 2 &amp; 5\n\\end{array}\\right)\\]</span></p>",
      "order": 1
    },
    {
      "id": "block_2",
      "type": "question",
      "latex": "Quelles sont les matrices carrées et les matrices symétriques ?",
      "html": "<p>Quelles sont les matrices carrées et les matrices symétriques ?</p>",
      "order": 2
    },
    {
      "id": "block_3",
      "type": "question",
      "latex": "Quels sont les produits matriciels (de 2 matrices) possibles ?",
      "html": "<p>Quels sont les produits matriciels (de 2 matrices) possibles ?</p>",
      "order": 3
    },
    {
      "id": "block_4",
      "type": "reponse",
      "latex": "$A$ est une matrice $1 \\times 3, B$ est une matrice $2 \\times 1, C$ est une matrice $3 \\times 2, D$ est une matrice $2 \\times 2$ et $E$ est une matrice $3 \\times 3$.\n \tSeules $D$ et $E$ sont des matrices carrées.\n \tDe ces deux matrices carrées, la seule qui est symétrique est la matrice $D$.\n \t\n \tLes produits possibles sont :\n \\begin{enumerate}\n \t\\item $A\\times C$ et la matrice produit est de type $1 \\times 2$ ;\n \t\\item $A\\times E$ et la matrice produit est de type $1 \\times 3$ ;\n \t\\item $B\\times A$ et la matrice produit est de type $2 \\times 3$ ;\n \t\\item $C \\times B$ et la matrice produit est de type $3 \\times 1$ ;\n \t\\item $C\\times D$ et la matrice produit est de type $3 \\times 2$ ;\n \t\\item $D \\times B$ et la matrice produit est de type $2 \\times 1$ ;\n \t\\item $D\\times D = D^2$ et la matrice produit est de type $2 \\times 2$ ;\n \t\\item $E \\times C$ et la matrice produit est de type $3 \\times 2$ ;\n \t\\item $E \\times E$ et la matrice produit est de type $3 \\times 3$ ;\n \\end{enumerate}",
      "html": "<p><span class=\"math inline\">\\(A\\)</span> est une matrice <span class=\"math inline\">\\(1 \\times 3, B\\)</span> est une matrice <span class=\"math inline\">\\(2 \\times 1, C\\)</span> est une matrice <span class=\"math inline\">\\(3 \\times 2, D\\)</span> est une matrice <span class=\"math inline\">\\(2 \\times 2\\)</span> et <span class=\"math inline\">\\(E\\)</span> est une matrice <span class=\"math inline\">\\(3 \\times 3\\)</span>.\nSeules <span class=\"math inline\">\\(D\\)</span> et <span class=\"math inline\">\\(E\\)</span> sont des matrices carrées.\nDe ces deux matrices carrées, la seule qui est symétrique est la matrice <span class=\"math inline\">\\(D\\)</span>.</p>\n<p>Les produits possibles sont :</p>\n<ol>\n<li><p><span class=\"math inline\">\\(A\\times C\\)</span> et la matrice produit est de type <span class=\"math inline\">\\(1 \\times 2\\)</span> ;</p></li>\n<li><p><span class=\"math inline\">\\(A\\times E\\)</span> et la matrice produit est de type <span class=\"math inline\">\\(1 \\times 3\\)</span> ;</p></li>\n<li><p><span class=\"math inline\">\\(B\\times A\\)</span> et la matrice produit est de type <span class=\"math inline\">\\(2 \\times 3\\)</span> ;</p></li>\n<li><p><span class=\"math inline\">\\(C \\times B\\)</span> et la matrice produit est de type <span class=\"math inline\">\\(3 \\times 1\\)</span> ;</p></li>\n<li><p><span class=\"math inline\">\\(C\\times D\\)</span> et la matrice produit est de type <span class=\"math inline\">\\(3 \\times 2\\)</span> ;</p></li>\n<li><p><span class=\"math inline\">\\(D \\times B\\)</span> et la matrice produit est de type <span class=\"math inline\">\\(2 \\times 1\\)</span> ;</p></li>\n<li><p><span class=\"math inline\">\\(D\\times D = D^2\\)</span> et la matrice produit est de type <span class=\"math inline\">\\(2 \\times 2\\)</span> ;</p></li>\n<li><p><span class=\"math inline\">\\(E \\times C\\)</span> et la matrice produit est de type <span class=\"math inline\">\\(3 \\times 2\\)</span> ;</p></li>\n<li><p><span class=\"math inline\">\\(E \\times E\\)</span> et la matrice produit est de type <span class=\"math inline\">\\(3 \\times 3\\)</span> ;</p></li>\n</ol>",
      "order": 4
    }
  ],
  "artifacts": {
    "tikz": [],
    "geogebra": [],
    "code": [],
    "video": null
  },
  "source_hash": "d68f497cc978854e9d7699ebc1ed4f73d402381809b873846890af459b6d114c"
}