{
  "uuid": "ycEr",
  "title": "Regression linéaire",
  "chapter": "Optimisation",
  "subchapter": "Autre",
  "theme": "optimisation",
  "difficulty": null,
  "author": "Erwan HILLION",
  "organization": "AMSCC",
  "video_id": "",
  "created_at": "2024-10-01",
  "updated_at": "2025-08-25T13:15:40.586Z",
  "content": [
    {
      "id": "block_1",
      "type": "text",
      "latex": "On dispose d'observations $(x_1,y_1),\\ldots,(x_n,y_n)$. On cherche les \"meilleurs\" coefficients $a$ et $b$ tels que pour chaque observation, on ait $y_i \\approx a x_i + b$. Ce probl\\`eme est appel\\'e r\\'egression lin\\'eaire simple.\n\n\\medskip\n\nPour mesurer la qualit\\'e des param\\`etres $(a,b)$, on souhaite que l'\\'ecart entre $y_i$ et $ax_i+b$ soit faible pour chaque observation. Pour quantifier l'erreur, on utilise le risque quadratique :\n\\begin{equation*}\nR(a,b) = \\sum_{i=1}^n (y_i - (a x_i+b) )^2.\n\\end{equation*}\nLe probl\\`eme est de minimiser la fonction $R(a,b)$.",
      "html": "<p>On dispose d’observations <span class=\"math inline\">\\((x_1,y_1),\\ldots,(x_n,y_n)\\)</span>. On cherche les \"meilleurs\" coefficients <span class=\"math inline\">\\(a\\)</span> et <span class=\"math inline\">\\(b\\)</span> tels que pour chaque observation, on ait <span class=\"math inline\">\\(y_i \\approx a x_i + b\\)</span>. Ce problème est appelé régression linéaire simple.</p>\n<p>Pour mesurer la qualité des paramètres <span class=\"math inline\">\\((a,b)\\)</span>, on souhaite que l’écart entre <span class=\"math inline\">\\(y_i\\)</span> et <span class=\"math inline\">\\(ax_i+b\\)</span> soit faible pour chaque observation. Pour quantifier l’erreur, on utilise le risque quadratique :\n<span class=\"math display\">\\[\\begin{equation}\nR(a,b) = \\sum_{i=1}^n (y_i - (a x_i+b) )^2.\n\\end{equation}\\]</span>\nLe problème est de minimiser la fonction <span class=\"math inline\">\\(R(a,b)\\)</span>.</p>",
      "order": 1
    },
    {
      "id": "block_2",
      "type": "question",
      "latex": "Montrer que :\n\\begin{equation*}\nR(a,b) = a^2 \\sum_{i=1}^n x_i^2 + 2ab \\sum_{i=1}^n x_i + b^2 n -2 a\\sum_{i=1}^n x_i y_i -2 b \\sum_{i=1}^n y_i + \\sum_{i=1}^n y_i^2.\n\\end{equation*}",
      "html": "<p>Montrer que :\n<span class=\"math display\">\\[\\begin{equation}\nR(a,b) = a^2 \\sum_{i=1}^n x_i^2 + 2ab \\sum_{i=1}^n x_i + b^2 n -2 a\\sum_{i=1}^n x_i y_i -2 b \\sum_{i=1}^n y_i + \\sum_{i=1}^n y_i^2.\n\\end{equation}\\]</span></p>",
      "order": 2
    },
    {
      "id": "block_3",
      "type": "reponse",
      "latex": "La formule s'obtient simplement en développant chaque expression de la somme.",
      "html": "<p>La formule s’obtient simplement en développant chaque expression de la somme.</p>",
      "order": 3
    },
    {
      "id": "block_4",
      "type": "question",
      "latex": "Montrer que le gradient de $R$ s'écrit : \n\\begin{equation} \\label{eq:nablaR}\n(\\nabla R)(a,b) = \\left( \\begin{array}{c} 2a \\sum_{i=1}^n x_i^2 + 2 b \\sum_{i=1}^n x_i -2 \\sum_{i=1}^n x_i y_i \\\\ 2a \\sum_{i=1}^n x_i +2 b n -2 \\sum_{i=1}^n y_i \\end{array} \\right).\n\\end{equation}",
      "html": "<p>Montrer que le gradient de <span class=\"math inline\">\\(R\\)</span> s’écrit :\n<span class=\"math display\">\\[\\begin{equation} \\label{eq:nablaR}\n(\\nabla R)(a,b) = \\left( \\begin{array}{c} 2a \\sum_{i=1}^n x_i^2 + 2 b \\sum_{i=1}^n x_i -2 \\sum_{i=1}^n x_i y_i \\\\ 2a \\sum_{i=1}^n x_i +2 b n -2 \\sum_{i=1}^n y_i \\end{array} \\right).\n\\end{equation}\\]</span></p>",
      "order": 4
    },
    {
      "id": "block_5",
      "type": "reponse",
      "latex": "Cela découle d'un calcul direct.",
      "html": "<p>Cela découle d’un calcul direct.</p>",
      "order": 5
    },
    {
      "id": "block_6",
      "type": "question",
      "latex": "Montrer que $R$ possède un unique point critique $(a^*,b^*)$ que l'on exprimera à l'aide des $x_i$ et des $y_i$.",
      "html": "<p>Montrer que <span class=\"math inline\">\\(R\\)</span> possède un unique point critique <span class=\"math inline\">\\((a^*,b^*)\\)</span> que l’on exprimera à l’aide des <span class=\"math inline\">\\(x_i\\)</span> et des <span class=\"math inline\">\\(y_i\\)</span>.</p>",
      "order": 6
    },
    {
      "id": "block_7",
      "type": "reponse",
      "latex": "On cherche $(a^*,b^*)$ tel que $\\nabla R(a^*,b^*)=0$. Au vu de l'expression explicite du gradient, on s'aperçoit qu'il faut résoudre un système linéaire à deux inconnues. La résolution de ce système (par exemple avec le pivot de Gauss) donne l'unique solution : $$a^* = \\frac{\\sum_{i=1}^n x_i \\sum_{i=1}^n y_i - n \\sum_{i=1}^n x_iy_i}{\\left(\\sum_{i=1}^n x_i\\right)^2-n\\sum_{i=1}^n x_i^2} \\ , \\ b^*=\\frac{\\sum_{i=1}^n x_iy_i \\sum_{i=1}^n x_i-\\sum_{i=1}^n y_i \\sum_{i=1}^n x_i^2}{\\left(\\sum_{i=1}^n x_i\\right)^2-n\\sum_{i=1}^n x_i^2}.$$",
      "html": "<p>On cherche <span class=\"math inline\">\\((a^*,b^*)\\)</span> tel que <span class=\"math inline\">\\(\\nabla R(a^*,b^*)=0\\)</span>. Au vu de l’expression explicite du gradient, on s’aperçoit qu’il faut résoudre un système linéaire à deux inconnues. La résolution de ce système (par exemple avec le pivot de Gauss) donne l’unique solution : <span class=\"math display\">\\[a^* = \\frac{\\sum_{i=1}^n x_i \\sum_{i=1}^n y_i - n \\sum_{i=1}^n x_iy_i}{\\left(\\sum_{i=1}^n x_i\\right)^2-n\\sum_{i=1}^n x_i^2} \\ , \\ b^*=\\frac{\\sum_{i=1}^n x_iy_i \\sum_{i=1}^n x_i-\\sum_{i=1}^n y_i \\sum_{i=1}^n x_i^2}{\\left(\\sum_{i=1}^n x_i\\right)^2-n\\sum_{i=1}^n x_i^2}.\\]</span></p>",
      "order": 7
    },
    {
      "id": "block_8",
      "type": "question",
      "latex": "Montrer que la hessienne de $R$ s'écrit :\n\\begin{equation*}\n\\textrm{Hess}_R(a,b)  = \\left( \\begin{array}{cc} 2 \\sum_{i=1}^n x_i^2 & 2 \\sum_{i=1}^n x_i \\\\ 2 \\sum_{i=1}^n x_i & 2 n \\end{array}\\right).\n\\end{equation*}",
      "html": "<p>Montrer que la hessienne de <span class=\"math inline\">\\(R\\)</span> s’écrit :\n<span class=\"math display\">\\[\\begin{equation}\n\\textrm{Hess}_R(a,b)  = \\left( \\begin{array}{cc} 2 \\sum_{i=1}^n x_i^2 &amp; 2 \\sum_{i=1}^n x_i \\\\ 2 \\sum_{i=1}^n x_i &amp; 2 n \\end{array}\\right).\n\\end{equation}\\]</span></p>",
      "order": 8
    },
    {
      "id": "block_9",
      "type": "reponse",
      "latex": "La hessienne s'obtient par calcul direct, en dérivant les dérivées partielles obtenues dans le calcul du gradient.",
      "html": "<p>La hessienne s’obtient par calcul direct, en dérivant les dérivées partielles obtenues dans le calcul du gradient.</p>",
      "order": 9
    },
    {
      "id": "block_10",
      "type": "reponse",
      "latex": "On peut remarquer que la hessienne est constante en $a$ et $b$ (car la fonciton $R$ est polynomiale de degré $2$). Il suffit donc de montrer que $\\langle X, H X \\rangle \\ge 0$ pour tout vecteur $X = \\begin{pmatrix} a \\\\ b \\end{pmatrix} \\in \\R^2$, où $H$ est la hessienne obtenue précédemment. Ce produit scalaire s'écrit, après développement : $$ \\frac{1}{4} \\langle X, H X \\rangle = a^2 \\sum_{i=1}^n x_i^2 + 2 a b \\sum_{i=1}^n x_i  + b^2 n.$$ Par Cauchy-Schwarz, on a $\\sum_{i=1}^n x_i^2 \\ge \\frac{1}{n} \\left(\\sum_{i=1}^n x_i \\right)^2$, d'où il vient : $$ \\frac{1}{4} \\langle X, H X \\rangle  \\ge \\frac{1}{n}\\left(a \\sum_{i=1}^n x_i + b n \\right)^2 \\ge 0,$$ comme voulu.",
      "html": "<p>On peut remarquer que la hessienne est constante en <span class=\"math inline\">\\(a\\)</span> et <span class=\"math inline\">\\(b\\)</span> (car la fonciton <span class=\"math inline\">\\(R\\)</span> est polynomiale de degré <span class=\"math inline\">\\(2\\)</span>). Il suffit donc de montrer que <span class=\"math inline\">\\(\\langle X, H X \\rangle \\ge 0\\)</span> pour tout vecteur <span class=\"math inline\">\\(X = \\begin{pmatrix} a \\\\ b \\end{pmatrix} \\in \\R^2\\)</span>, où <span class=\"math inline\">\\(H\\)</span> est la hessienne obtenue précédemment. Ce produit scalaire s’écrit, après développement : <span class=\"math display\">\\[\\frac{1}{4} \\langle X, H X \\rangle = a^2 \\sum_{i=1}^n x_i^2 + 2 a b \\sum_{i=1}^n x_i  + b^2 n.\\]</span> Par Cauchy-Schwarz, on a <span class=\"math inline\">\\(\\sum_{i=1}^n x_i^2 \\ge \\frac{1}{n} \\left(\\sum_{i=1}^n x_i \\right)^2\\)</span>, d’où il vient : <span class=\"math display\">\\[\\frac{1}{4} \\langle X, H X \\rangle  \\ge \\frac{1}{n}\\left(a \\sum_{i=1}^n x_i + b n \\right)^2 \\ge 0,\\]</span> comme voulu.</p>",
      "order": 10
    }
  ],
  "artifacts": {
    "tikz": [],
    "geogebra": [],
    "code": [],
    "video": null
  },
  "source_hash": "4f82cc0c44074ae7a4c6a06b11671f41f11d29dc351ea6df35f17732712e5d0f"
}